earthscii/__init__.py
earthscii/etopo_loader.py
earthscii/globe_loader.py
earthscii/globe_projection.py
earthscii/globe_tile_manager.py
earthscii/main.py
earthscii/map_loader.py
earthscii/projection.py
earthscii/renderer.py
earthscii/tile_fetcher.py
earthscii/utils.py
earthscii/data/n37_w123_1arc_v3.tif
earthscii-0.1.19.dist-info/licenses/LICENSE
earthscii-0.1.19.dist-info/METADATA
earthscii-0.1.19.dist-info/WHEEL
earthscii-0.1.19.dist-info/entry_points.txt
earthscii-0.1.19.dist-info/top_level.txt
earthscii-0.1.19.dist-info/RECORD
