Metadata-Version: 2.4
Name: earthscii
Version: 0.1.19
Summary: Terminal-based 3D terrain viewer.
Author-email: Lennier Mulder <lenniermulder@icloud.com>
License-Expression: GPL-3.0-or-later
Requires-Python: >=3.8
License-File: LICENSE
Requires-Dist: numpy
Requires-Dist: rasterio
Dynamic: license-file
